README.md
setup.py
Minicash.egg-info/PKG-INFO
Minicash.egg-info/SOURCES.txt
Minicash.egg-info/dependency_links.txt
Minicash.egg-info/not-zip-safe
Minicash.egg-info/requires.txt
Minicash.egg-info/top_level.txt
minicash/minicash
minicash/minicashd
minicash/quickDataGen
minicash/utils/checksum.py
minicash/utils/client.py
minicash/utils/gpg.py
minicash/utils/init.py
minicash/utils/parsers.py
minicash/utils/pow.py
minicash/utils/protocols.py