Metadata-Version: 1.1
Name: Minicash
Version: 0.4.0
Summary: A cryptocurrency without blockchain
Home-page: http://github.com/saavedra29/Minicash
Author: Aristides Tomaras
Author-email: arisgold29@gmail.com
License: MIT
Keywords: Cryptocurrency gpg
Platform: UNKNOWN
Classifier: Development Status :: 3 - Alpha
Classifier: Environment :: Console
Classifier: Framework :: AsyncIO
Classifier: License :: OSI Approved :: MIT License
Classifier: Operating System :: POSIX :: Linux
Classifier: Programming Language :: Python :: 3.5
Classifier: Programming Language :: Python :: 3.6
Classifier: Topic :: Security :: Cryptography
